qx_rest/__init__.py
qx_rest-0.0.2.dist-info/LICENSE
qx_rest-0.0.2.dist-info/METADATA
qx_rest-0.0.2.dist-info/WHEEL
qx_rest-0.0.2.dist-info/top_level.txt
qx_rest-0.0.2.dist-info/RECORD
