Metadata-Version: 2.1
Name: qx-rest
Version: 0.0.2
Summary: Simple REST interface to the Phabrix Qx
Home-page: https://github.com/UndyingScroll
Author: Kevin Pulley
Author-email: kpulley@imaginecommunications.com
License: UNKNOWN
Platform: UNKNOWN
Classifier: Programming Language :: Python :: 3
Classifier: License :: OSI Approved :: MIT License
Classifier: Operating System :: OS Independent
Requires-Python: >=3.6
